languagestring
